wrapper_secrets_manager/__init__.py
wrapper_secrets_manager/wrapper_secrets_manager.py
wrapper_secrets_manager-0.0.1.dist-info/METADATA
wrapper_secrets_manager-0.0.1.dist-info/WHEEL
wrapper_secrets_manager-0.0.1.dist-info/top_level.txt
wrapper_secrets_manager-0.0.1.dist-info/RECORD
